gpicalc/__classes.py
gpicalc/__init__.py
gpicalc-0.6.0.dist-info/METADATA
gpicalc-0.6.0.dist-info/WHEEL
gpicalc-0.6.0.dist-info/top_level.txt
gpicalc-0.6.0.dist-info/RECORD
