Metadata-Version: 2.1
Name: gpicalc
Version: 0.6.0
Summary: a package for calculating global performance indicator (GPI)
Home-page: https://github.com/planta94/gpicalc
Author: M.Y. Chia
Author-email: chiamy94@gmail.com
License: UNKNOWN
Platform: UNKNOWN
Classifier: Programming Language :: Python :: 3
Classifier: License :: OSI Approved :: MIT License
Classifier: Operating System :: OS Independent
Requires-Python: >=3.6
